README.md
setup.py
heuristiciohbsp/bsp.py
heuristiciohbsp/quick_ioh.py
heuristiciohbsp.egg-info/PKG-INFO
heuristiciohbsp.egg-info/SOURCES.txt
heuristiciohbsp.egg-info/dependency_links.txt
heuristiciohbsp.egg-info/top_level.txt