Metadata-Version: 2.1
Name: heuristiciohbsp
Version: 1.0.0
Summary: Heuristic Methods for Minimizing Cut Bars and Using Leftovers from the One-dimensional Cutting Process
Home-page: https://github.com/omatheuspimenta/heuristiciohbsp
Author: Matheus Pimenta
Author-email: matheus.pimenta@outlook.com
License: MIT License
Keywords: Heuristic_IOHBSP
Platform: UNKNOWN
